lavague/drivers/selenium/__init__.py
lavague/drivers/selenium/base.py
lavague/drivers/selenium/javascript.py
lavague/drivers/selenium/listener.py
lavague_drivers_selenium-0.2.14.dist-info/METADATA
lavague_drivers_selenium-0.2.14.dist-info/WHEEL
lavague_drivers_selenium-0.2.14.dist-info/RECORD
